LICENSE
README.md
setup.py
datasette_render_xlsx/__init__.py
datasette_render_xlsx.egg-info/PKG-INFO
datasette_render_xlsx.egg-info/SOURCES.txt
datasette_render_xlsx.egg-info/dependency_links.txt
datasette_render_xlsx.egg-info/entry_points.txt
datasette_render_xlsx.egg-info/requires.txt
datasette_render_xlsx.egg-info/top_level.txt