Metadata-Version: 2.1
Name: datasette-render-xlsx
Version: 0.1
Summary: Download tables as xlsx-file
Home-page: https://github.com/vitlais/datasette-render-xlsx
Author: Henrik Vitalis
License: Apache License, Version 2.0
Project-URL: Issues, https://github.com/vitlais/datasette-render-xlsx/issues
Project-URL: CI, https://github.com/vitlais/datasette-render-xlsx/actions
Project-URL: Changelog, https://github.com/vitlais/datasette-render-xlsx/releases
Classifier: Framework :: Datasette
Classifier: License :: OSI Approved :: Apache Software License
Requires-Python: >=3.7
Provides-Extra: test
License-File: LICENSE
